cursofiap/__init__.py
cursofiap/core.py
video_aula_fiap_thiago_99-1.0.0.dist-info/METADATA
video_aula_fiap_thiago_99-1.0.0.dist-info/WHEEL
video_aula_fiap_thiago_99-1.0.0.dist-info/top_level.txt
video_aula_fiap_thiago_99-1.0.0.dist-info/RECORD
